[{"id":91611,"type":"ind","competitor":{"number":309,"identifier":"M309","skater":{"id":1393,"firstName":"Conor","lastName":"Mcdermott-Mostowy","country":"USA","gender":"M","dateOfBirth":"1999-01-13","dateOfDeath":null,"isActive":true,"iocCode":"SSUSA11301199901","photo":"https://media.isuresults.eu/skater/2025/11/14/1393.png","personalBestUrl":"https://api.isuresults.eu/skaters/1393/personal-best/","created":"2018-10-12T14:03:23.840836Z","modified":"2026-01-01T19:56:54.915569Z"}},"startNumber":16,"startLane":"O","armband":"red","rank":1,"status":0,"time":"1:07.606","timeBehind":"0.000","reskate":0,"medal":null,"isOfficial":true,"finishPhoto":null,"created":"2026-01-03T01:30:51.914640Z","modified":"2026-01-03T22:47:39.521225Z","laps":[{"number":1,"time":"16.61","passageTime":"16.614","rank":2},{"number":2,"time":"24.51","passageTime":"41.126","rank":1},{"number":3,"time":"26.48","passageTime":"1:07.606","rank":1}]},{"id":91608,"type":"ind","competitor":{"number":310,"identifier":"M310","skater":{"id":1856,"firstName":"Cooper","lastName":"Mcleod","country":"USA","gender":"M","dateOfBirth":"2001-11-07","dateOfDeath":null,"isActive":true,"iocCode":"SSUSA10711200101","photo":"https://media.isuresults.eu/skater/2025/11/14/1856.png","personalBestUrl":"https://api.isuresults.eu/skaters/1856/personal-best/","created":"2021-11-11T14:18:19.179424Z","modified":"2026-01-01T19:56:54.921335Z"}},"startNumber":15,"startLane":"I","armband":"white","rank":2,"status":0,"time":"1:07.845","timeBehind":"0.239","reskate":0,"medal":null,"isOfficial":true,"finishPhoto":null,"created":"2026-01-03T01:30:51.907623Z","modified":"2026-01-03T22:47:39.538862Z","laps":[{"number":1,"time":"16.35","passageTime":"16.356","rank":1},{"number":2,"time":"24.79","passageTime":"41.154","rank":2},{"number":3,"time":"26.69","passageTime":"1:07.845","rank":2}]},{"id":91610,"type":"ind","competitor":{"number":324,"identifier":"M324","skater":{"id":1726,"firstName":"Jordan","lastName":"Stolz","country":"USA","gender":"M","dateOfBirth":"2004-05-21","dateOfDeath":null,"isActive":true,"iocCode":"SSUSA12105200401","photo":"https://media.isuresults.eu/skater/2025/11/14/1726.png","personalBestUrl":"https://api.isuresults.eu/skaters/1726/personal-best/","created":"2019-11-15T18:51:03.583514Z","modified":"2026-01-01T19:56:54.999315Z"}},"startNumber":16,"startLane":"I","armband":"white","rank":3,"status":0,"time":"1:07.968","timeBehind":"0.362","reskate":0,"medal":null,"isOfficial":true,"finishPhoto":null,"created":"2026-01-03T01:30:51.912294Z","modified":"2026-01-03T22:47:39.554749Z","laps":[{"number":1,"time":"17.44","passageTime":"17.442","rank":10},{"number":2,"time":"24.55","passageTime":"41.994","rank":4},{"number":3,"time":"25.97","passageTime":"1:07.968","rank":3}]},{"id":91609,"type":"ind","competitor":{"number":344,"identifier":"M344","skater":{"id":1981,"firstName":"Zach","lastName":"Stoppelmoor","country":"USA","gender":"M","dateOfBirth":"1999-05-11","dateOfDeath":null,"isActive":true,"iocCode":"SSUSA11105199901","photo":"https://media.isuresults.eu/skater/2025/11/14/1981.png","personalBestUrl":"https://api.isuresults.eu/skaters/1981/personal-best/","created":"2021-11-29T22:52:47.885607Z","modified":"2026-01-01T19:56:55.129488Z"}},"startNumber":15,"startLane":"O","armband":"red","rank":4,"status":0,"time":"1:08.404","timeBehind":"0.798","reskate":0,"medal":null,"isOfficial":true,"finishPhoto":null,"created":"2026-01-03T01:30:51.909905Z","modified":"2026-01-03T22:47:39.573770Z","laps":[{"number":1,"time":"16.65","passageTime":"16.654","rank":3},{"number":2,"time":"24.83","passageTime":"41.491","rank":3},{"number":3,"time":"26.91","passageTime":"1:08.404","rank":4}]},{"id":91605,"type":"ind","competitor":{"number":335,"identifier":"M335","skater":{"id":2440,"firstName":"Max","lastName":"Weber","country":"USA","gender":"M","dateOfBirth":"2007-08-19","dateOfDeath":null,"isActive":true,"iocCode":"SSUSA11908200701","photo":null,"personalBestUrl":"https://api.isuresults.eu/skaters/2440/personal-best/","created":"2024-01-30T10:34:26.288909Z","modified":"2026-01-01T19:56:55.073813Z"}},"startNumber":13,"startLane":"O","armband":"red","rank":5,"status":0,"time":"1:09.447","timeBehind":"1.841","reskate":0,"medal":null,"isOfficial":true,"finishPhoto":null,"created":"2026-01-03T01:30:51.900870Z","modified":"2026-01-03T22:47:39.590464Z","laps":[{"number":1,"time":"17.18","passageTime":"17.184","rank":6},{"number":2,"time":"25.44","passageTime":"42.624","rank":7},{"number":3,"time":"26.82","passageTime":"1:09.447","rank":5}]},{"id":91613,"type":"ind","competitor":{"number":313,"identifier":"M313","skater":{"id":580,"firstName":"Emery","lastName":"Lehman","country":"USA","gender":"M","dateOfBirth":"1996-06-13","dateOfDeath":null,"isActive":true,"iocCode":"SSUSA11306199601","photo":"https://media.isuresults.eu/skater/2025/11/14/580.png","personalBestUrl":"https://api.isuresults.eu/skaters/580/personal-best/","created":"2017-10-28T13:31:01.985828Z","modified":"2026-01-01T19:56:54.937547Z"}},"startNumber":17,"startLane":"O","armband":"red","rank":6,"status":0,"time":"1:09.547","timeBehind":"1.941","reskate":0,"medal":null,"isOfficial":true,"finishPhoto":null,"created":"2026-01-03T01:30:51.919142Z","modified":"2026-01-03T22:47:39.607197Z","laps":[{"number":1,"time":"17.47","passageTime":"17.478","rank":11},{"number":2,"time":"25.72","passageTime":"43.203","rank":8},{"number":3,"time":"26.34","passageTime":"1:09.547","rank":6}]},{"id":91606,"type":"ind","competitor":{"number":305,"identifier":"M305","skater":{"id":1217,"firstName":"Austin","lastName":"Kleba","country":"USA","gender":"M","dateOfBirth":"1999-07-27","dateOfDeath":null,"isActive":true,"iocCode":"SSUSA12707199901","photo":"https://media.isuresults.eu/skater/2025/11/14/1217.png","personalBestUrl":"https://api.isuresults.eu/skaters/1217/personal-best/","created":"2018-01-31T16:00:08.665733Z","modified":"2026-01-01T19:56:54.891928Z"}},"startNumber":14,"startLane":"I","armband":"white","rank":7,"status":0,"time":"1:10.077","timeBehind":"2.471","reskate":0,"medal":null,"isOfficial":true,"finishPhoto":null,"created":"2026-01-03T01:30:51.903113Z","modified":"2026-01-03T22:47:39.625686Z","laps":[{"number":1,"time":"16.84","passageTime":"16.841","rank":5},{"number":2,"time":"25.43","passageTime":"42.278","rank":6},{"number":3,"time":"27.79","passageTime":"1:10.077","rank":7}]},{"id":91607,"type":"ind","competitor":{"number":341,"identifier":"M341","skater":{"id":1996,"firstName":"Tanner","lastName":"Worley","country":"USA","gender":"M","dateOfBirth":"1997-12-18","dateOfDeath":null,"isActive":true,"iocCode":"SSUSA11812199701","photo":null,"personalBestUrl":"https://api.isuresults.eu/skaters/1996/personal-best/","created":"2021-12-14T21:00:01.021108Z","modified":"2026-01-01T19:56:55.110793Z"}},"startNumber":14,"startLane":"O","armband":"red","rank":8,"status":0,"time":"1:10.204","timeBehind":"2.598","reskate":0,"medal":null,"isOfficial":true,"finishPhoto":null,"created":"2026-01-03T01:30:51.905470Z","modified":"2026-01-03T22:47:39.643386Z","laps":[{"number":1,"time":"16.68","passageTime":"16.689","rank":4},{"number":2,"time":"25.39","passageTime":"42.084","rank":5},{"number":3,"time":"28.12","passageTime":"1:10.204","rank":8}]},{"id":91612,"type":"ind","competitor":{"number":323,"identifier":"M323","skater":{"id":1594,"firstName":"Jonathan","lastName":"Tobon","country":"USA","gender":"M","dateOfBirth":"2003-11-25","dateOfDeath":null,"isActive":true,"iocCode":"SSUSA12511200301","photo":"https://media.isuresults.eu/skater/2025/11/14/1594.png","personalBestUrl":"https://api.isuresults.eu/skaters/1594/personal-best/","created":"2019-02-04T19:59:23.221402Z","modified":"2026-01-01T19:56:54.993601Z"}},"startNumber":17,"startLane":"I","armband":"white","rank":9,"status":0,"time":"1:10.951","timeBehind":"3.345","reskate":0,"medal":null,"isOfficial":true,"finishPhoto":null,"created":"2026-01-03T01:30:51.916818Z","modified":"2026-01-03T22:47:39.659424Z","laps":[{"number":1,"time":"17.26","passageTime":"17.262","rank":7},{"number":2,"time":"26.03","passageTime":"43.295","rank":9},{"number":3,"time":"27.65","passageTime":"1:10.951","rank":9}]},{"id":91603,"type":"ind","competitor":{"number":303,"identifier":"M303","skater":{"id":2011,"firstName":"Auggie","lastName":"Herman","country":"USA","gender":"M","dateOfBirth":"2003-08-03","dateOfDeath":null,"isActive":true,"iocCode":"SSUSA10308200301","photo":null,"personalBestUrl":"https://api.isuresults.eu/skaters/2011/personal-best/","created":"2022-01-04T19:15:16.499370Z","modified":"2026-01-01T19:56:54.880736Z"}},"startNumber":12,"startLane":"O","armband":"red","rank":10,"status":0,"time":"1:11.861","timeBehind":"4.255","reskate":0,"medal":null,"isOfficial":true,"finishPhoto":null,"created":"2026-01-03T01:30:51.896611Z","modified":"2026-01-03T22:47:39.674928Z","laps":[{"number":1,"time":"17.39","passageTime":"17.397","rank":9},{"number":2,"time":"26.26","passageTime":"43.659","rank":11},{"number":3,"time":"28.20","passageTime":"1:11.861","rank":10}]},{"id":91598,"type":"ind","competitor":{"number":330,"identifier":"M330","skater":{"id":2588,"firstName":"Leo","lastName":"Drossos-Thompson","country":"USA","gender":"M","dateOfBirth":"2006-01-20","dateOfDeath":null,"isActive":true,"iocCode":"SSUSA12001200601","photo":null,"personalBestUrl":"https://api.isuresults.eu/skaters/2588/personal-best/","created":"2025-01-06T19:28:48.411707Z","modified":"2026-01-01T19:56:55.043951Z"}},"startNumber":10,"startLane":"I","armband":"white","rank":11,"status":0,"time":"1:12.433","timeBehind":"4.827","reskate":0,"medal":null,"isOfficial":true,"finishPhoto":null,"created":"2026-01-03T01:30:51.884963Z","modified":"2026-01-03T22:47:39.690832Z","laps":[{"number":1,"time":"17.63","passageTime":"17.635","rank":15},{"number":2,"time":"26.33","passageTime":"43.973","rank":12},{"number":3,"time":"28.46","passageTime":"1:12.433","rank":11}]},{"id":91602,"type":"ind","competitor":{"number":320,"identifier":"M320","skater":{"id":1815,"firstName":"Ian","lastName":"Frederick","country":"USA","gender":"M","dateOfBirth":"2002-06-07","dateOfDeath":null,"isActive":true,"iocCode":"SSUSA10706200201","photo":null,"personalBestUrl":"https://api.isuresults.eu/skaters/1815/personal-best/","created":"2020-02-12T14:53:08.692258Z","modified":"2026-01-01T19:56:54.977164Z"}},"startNumber":12,"startLane":"I","armband":"white","rank":12,"status":0,"time":"1:13.475","timeBehind":"5.869","reskate":0,"medal":null,"isOfficial":true,"finishPhoto":null,"created":"2026-01-03T01:30:51.894302Z","modified":"2026-01-03T22:47:39.707525Z","laps":[{"number":1,"time":"17.54","passageTime":"17.547","rank":13},{"number":2,"time":"26.96","passageTime":"44.515","rank":13},{"number":3,"time":"28.96","passageTime":"1:13.475","rank":12}]},{"id":91593,"type":"ind","competitor":{"number":315,"identifier":"M315","skater":{"id":2765,"firstName":"Finn","lastName":"Siebert","country":"USA","gender":"M","dateOfBirth":"2006-08-17","dateOfDeath":null,"isActive":true,"iocCode":"SSUSA11708200601","photo":null,"personalBestUrl":"https://api.isuresults.eu/skaters/2765/personal-best/","created":"2025-12-31T14:43:36.405221Z","modified":"2026-01-01T19:56:54.949078Z"}},"startNumber":7,"startLane":"O","armband":"red","rank":13,"status":0,"time":"1:13.592","timeBehind":"5.986","reskate":0,"medal":null,"isOfficial":true,"finishPhoto":null,"created":"2026-01-03T01:30:51.872400Z","modified":"2026-01-03T22:47:39.726991Z","laps":[{"number":1,"time":"17.88","passageTime":"17.881","rank":22},{"number":2,"time":"26.68","passageTime":"44.562","rank":15},{"number":3,"time":"29.03","passageTime":"1:13.592","rank":13}]},{"id":91597,"type":"ind","competitor":{"number":317,"identifier":"M317","skater":{"id":2767,"firstName":"George","lastName":"Wheelock","country":"USA","gender":"M","dateOfBirth":"2002-03-16","dateOfDeath":null,"isActive":true,"iocCode":"SSUSA11603200201","photo":null,"personalBestUrl":"https://api.isuresults.eu/skaters/2767/personal-best/","created":"2025-12-31T14:43:55.396859Z","modified":"2026-01-01T19:56:54.960060Z"}},"startNumber":9,"startLane":"O","armband":"red","rank":14,"status":0,"time":"1:13.709","timeBehind":"6.103","reskate":0,"medal":null,"isOfficial":true,"finishPhoto":null,"created":"2026-01-03T01:30:51.882704Z","modified":"2026-01-03T22:47:39.744108Z","laps":[{"number":1,"time":"17.71","passageTime":"17.710","rank":17},{"number":2,"time":"26.84","passageTime":"44.553","rank":14},{"number":3,"time":"29.15","passageTime":"1:13.709","rank":14}]},{"id":91599,"type":"ind","competitor":{"number":319,"identifier":"M319","skater":{"id":2009,"firstName":"Herb","lastName":"Harbison","country":"USA","gender":"M","dateOfBirth":"1997-04-01","dateOfDeath":null,"isActive":true,"iocCode":"SSUSA10104199701","photo":null,"personalBestUrl":"https://api.isuresults.eu/skaters/2009/personal-best/","created":"2022-01-04T19:14:52.210920Z","modified":"2026-01-01T19:56:54.971595Z"}},"startNumber":10,"startLane":"O","armband":"red","rank":15,"status":0,"time":"1:13.720","timeBehind":"6.114","reskate":0,"medal":null,"isOfficial":true,"finishPhoto":null,"created":"2026-01-03T01:30:51.887170Z","modified":"2026-01-03T22:47:39.760708Z","laps":[{"number":1,"time":"18.11","passageTime":"18.110","rank":24},{"number":2,"time":"26.65","passageTime":"44.769","rank":17},{"number":3,"time":"28.95","passageTime":"1:13.720","rank":15}]},{"id":91595,"type":"ind","competitor":{"number":339,"identifier":"M339","skater":{"id":2584,"firstName":"Sam","lastName":"Chamberlain","country":"USA","gender":"M","dateOfBirth":"2009-06-29","dateOfDeath":null,"isActive":true,"iocCode":"SSUSA12906200901","photo":null,"personalBestUrl":"https://api.isuresults.eu/skaters/2584/personal-best/","created":"2025-01-06T19:28:39.008391Z","modified":"2026-01-01T19:56:55.099382Z"}},"startNumber":8,"startLane":"O","armband":"red","rank":16,"status":0,"time":"1:14.054","timeBehind":"6.448","reskate":0,"medal":null,"isOfficial":true,"finishPhoto":null,"created":"2026-01-03T01:30:51.877473Z","modified":"2026-01-03T22:47:39.778657Z","laps":[{"number":1,"time":"17.90","passageTime":"17.902","rank":23},{"number":2,"time":"27.06","passageTime":"44.966","rank":20},{"number":3,"time":"29.08","passageTime":"1:14.054","rank":16}]},{"id":91596,"type":"ind","competitor":{"number":345,"identifier":"M345","skater":{"id":2777,"firstName":"Zachary","lastName":"Jensen","country":"USA","gender":"M","dateOfBirth":"2005-02-28","dateOfDeath":null,"isActive":true,"iocCode":"SSUSA12802200501","photo":null,"personalBestUrl":"https://api.isuresults.eu/skaters/2777/personal-best/","created":"2025-12-31T14:45:46.080923Z","modified":"2026-01-01T19:56:55.137661Z"}},"startNumber":9,"startLane":"I","armband":"white","rank":17,"status":0,"time":"1:14.176","timeBehind":"6.570","reskate":0,"medal":null,"isOfficial":true,"finishPhoto":null,"created":"2026-01-03T01:30:51.879721Z","modified":"2026-01-03T22:47:39.794946Z","laps":[{"number":1,"time":"17.82","passageTime":"17.828","rank":21},{"number":2,"time":"27.18","passageTime":"45.017","rank":21},{"number":3,"time":"29.15","passageTime":"1:14.176","rank":17}]},{"id":91600,"type":"ind","competitor":{"number":334,"identifier":"M334","skater":{"id":2017,"firstName":"Matthew","lastName":"Salm","country":"USA","gender":"M","dateOfBirth":"1995-08-25","dateOfDeath":null,"isActive":true,"iocCode":"SSUSA12508199501","photo":null,"personalBestUrl":"https://api.isuresults.eu/skaters/2017/personal-best/","created":"2022-01-04T19:16:42.831509Z","modified":"2026-01-01T19:56:55.067679Z"}},"startNumber":11,"startLane":"I","armband":"white","rank":18,"status":0,"time":"1:14.294","timeBehind":"6.688","reskate":0,"medal":null,"isOfficial":true,"finishPhoto":null,"created":"2026-01-03T01:30:51.889575Z","modified":"2026-01-03T22:47:39.810886Z","laps":[{"number":1,"time":"17.65","passageTime":"17.653","rank":16},{"number":2,"time":"27.19","passageTime":"44.848","rank":18},{"number":3,"time":"29.44","passageTime":"1:14.294","rank":18}]},{"id":91590,"type":"ind","competitor":{"number":325,"identifier":"M325","skater":{"id":2016,"firstName":"Jori","lastName":"Kola","country":"USA","gender":"M","dateOfBirth":"1999-07-27","dateOfDeath":null,"isActive":true,"iocCode":"SSUSA12707199902","photo":null,"personalBestUrl":"https://api.isuresults.eu/skaters/2016/personal-best/","created":"2022-01-04T19:16:27.050190Z","modified":"2026-01-01T19:56:55.008142Z"}},"startNumber":6,"startLane":"I","armband":"white","rank":19,"status":0,"time":"1:14.325","timeBehind":"6.719","reskate":0,"medal":null,"isOfficial":true,"finishPhoto":null,"created":"2026-01-03T01:30:51.864835Z","modified":"2026-01-03T22:47:39.827002Z","laps":[{"number":1,"time":"17.75","passageTime":"17.754","rank":18},{"number":2,"time":"26.95","passageTime":"44.707","rank":16},{"number":3,"time":"29.61","passageTime":"1:14.325","rank":19}]},{"id":91604,"type":"ind","competitor":{"number":338,"identifier":"M338","skater":{"id":2007,"firstName":"Sabien","lastName":"Tinson","country":"USA","gender":"M","dateOfBirth":"2001-01-21","dateOfDeath":null,"isActive":true,"iocCode":"SSUSA12101200101","photo":null,"personalBestUrl":"https://api.isuresults.eu/skaters/2007/personal-best/","created":"2022-01-04T19:13:10.221236Z","modified":"2026-01-01T19:56:55.093129Z"}},"startNumber":13,"startLane":"I","armband":"white","rank":20,"status":0,"time":"1:14.425","timeBehind":"6.819","reskate":0,"medal":null,"isOfficial":true,"finishPhoto":null,"created":"2026-01-03T01:30:51.898738Z","modified":"2026-01-03T22:47:39.843975Z","laps":[{"number":1,"time":"17.28","passageTime":"17.283","rank":8},{"number":2,"time":"26.17","passageTime":"43.455","rank":10},{"number":3,"time":"30.97","passageTime":"1:14.425","rank":20}]},{"id":91586,"type":"ind","competitor":{"number":327,"identifier":"M327","skater":{"id":1995,"firstName":"Kelin","lastName":"Dunfee","country":"USA","gender":"M","dateOfBirth":"1991-05-08","dateOfDeath":null,"isActive":true,"iocCode":"SSUSA10805199101","photo":"https://media.isuresults.eu/skater/2025/11/14/1995.png","personalBestUrl":"https://api.isuresults.eu/skaters/1995/personal-best/","created":"2021-12-14T20:57:37.078303Z","modified":"2026-01-01T19:56:55.022849Z"}},"startNumber":4,"startLane":"I","armband":"white","rank":21,"status":0,"time":"1:14.952","timeBehind":"7.346","reskate":0,"medal":null,"isOfficial":true,"finishPhoto":null,"created":"2026-01-03T01:30:51.854433Z","modified":"2026-01-03T22:47:39.859373Z","laps":[{"number":1,"time":"18.74","passageTime":"18.746","rank":32},{"number":2,"time":"27.83","passageTime":"46.580","rank":28},{"number":3,"time":"28.37","passageTime":"1:14.952","rank":21}]},{"id":91589,"type":"ind","competitor":{"number":304,"identifier":"M304","skater":{"id":2015,"firstName":"Austin","lastName":"Carlson","country":"USA","gender":"M","dateOfBirth":"1991-06-13","dateOfDeath":null,"isActive":true,"iocCode":"SSUSA11306199101","photo":null,"personalBestUrl":"https://api.isuresults.eu/skaters/2015/personal-best/","created":"2022-01-04T19:16:07.912729Z","modified":"2026-01-01T19:56:54.886327Z"}},"startNumber":5,"startLane":"O","armband":"red","rank":22,"status":0,"time":"1:15.033","timeBehind":"7.427","reskate":0,"medal":null,"isOfficial":true,"finishPhoto":null,"created":"2026-01-03T01:30:51.862334Z","modified":"2026-01-03T22:47:39.875937Z","laps":[{"number":1,"time":"17.56","passageTime":"17.564","rank":14},{"number":2,"time":"27.34","passageTime":"44.911","rank":19},{"number":3,"time":"30.12","passageTime":"1:15.033","rank":22}]},{"id":91588,"type":"ind","competitor":{"number":306,"identifier":"M306","skater":{"id":2018,"firstName":"Brian","lastName":"Bullard","country":"USA","gender":"M","dateOfBirth":"1994-07-19","dateOfDeath":null,"isActive":true,"iocCode":"SSUSA11907199401","photo":null,"personalBestUrl":"https://api.isuresults.eu/skaters/2018/personal-best/","created":"2022-01-04T19:17:19.189677Z","modified":"2026-01-01T19:56:54.897274Z"}},"startNumber":5,"startLane":"I","armband":"white","rank":23,"status":0,"time":"1:15.468","timeBehind":"7.862","reskate":0,"medal":null,"isOfficial":true,"finishPhoto":null,"created":"2026-01-03T01:30:51.859471Z","modified":"2026-01-03T22:47:39.893029Z","laps":[{"number":1,"time":"17.53","passageTime":"17.534","rank":12},{"number":2,"time":"27.48","passageTime":"45.022","rank":22},{"number":3,"time":"30.44","passageTime":"1:15.468","rank":23}]},{"id":91584,"type":"ind","competitor":{"number":332,"identifier":"M332","skater":{"id":2773,"firstName":"Maison","lastName":"Riley","country":"USA","gender":"M","dateOfBirth":"1998-04-09","dateOfDeath":null,"isActive":true,"iocCode":"SSUSA10904199801","photo":null,"personalBestUrl":"https://api.isuresults.eu/skaters/2773/personal-best/","created":"2025-12-31T14:44:59.308850Z","modified":"2026-01-01T19:56:55.055629Z"}},"startNumber":3,"startLane":"I","armband":"white","rank":24,"status":0,"time":"1:15.535","timeBehind":"7.929","reskate":0,"medal":null,"isOfficial":true,"finishPhoto":null,"created":"2026-01-03T01:30:51.848924Z","modified":"2026-01-03T22:47:39.910870Z","laps":[{"number":1,"time":"17.82","passageTime":"17.827","rank":19},{"number":2,"time":"28.23","passageTime":"46.060","rank":25},{"number":3,"time":"29.47","passageTime":"1:15.535","rank":24}]},{"id":91594,"type":"ind","competitor":{"number":300,"identifier":"M300","skater":{"id":2678,"firstName":"Aiden","lastName":"Meacham","country":"USA","gender":"M","dateOfBirth":"2007-04-09","dateOfDeath":null,"isActive":true,"iocCode":"SSUSA10904200701","photo":null,"personalBestUrl":"https://api.isuresults.eu/skaters/2678/personal-best/","created":"2025-11-11T14:18:27.059406Z","modified":"2026-01-01T19:56:54.863517Z"}},"startNumber":8,"startLane":"I","armband":"white","rank":25,"status":0,"time":"1:15.824","timeBehind":"8.218","reskate":0,"medal":null,"isOfficial":true,"finishPhoto":null,"created":"2026-01-03T01:30:51.874992Z","modified":"2026-01-03T22:47:39.931668Z","laps":[{"number":1,"time":"18.53","passageTime":"18.537","rank":28},{"number":2,"time":"27.95","passageTime":"46.490","rank":27},{"number":3,"time":"29.33","passageTime":"1:15.824","rank":25}]},{"id":91582,"type":"ind","competitor":{"number":302,"identifier":"M302","skater":{"id":2763,"firstName":"Anson","lastName":"Quinn","country":"USA","gender":"M","dateOfBirth":"2007-06-14","dateOfDeath":null,"isActive":true,"iocCode":"SSUSA11406200701","photo":null,"personalBestUrl":"https://api.isuresults.eu/skaters/2763/personal-best/","created":"2025-12-31T14:42:54.174283Z","modified":"2026-01-01T19:56:54.875149Z"}},"startNumber":2,"startLane":"I","armband":"white","rank":26,"status":0,"time":"1:15.986","timeBehind":"8.380","reskate":0,"medal":null,"isOfficial":true,"finishPhoto":null,"created":"2026-01-03T01:30:51.842911Z","modified":"2026-01-03T22:47:39.947831Z","laps":[{"number":1,"time":"18.26","passageTime":"18.261","rank":27},{"number":2,"time":"28.16","passageTime":"46.425","rank":26},{"number":3,"time":"29.56","passageTime":"1:15.986","rank":26}]},{"id":91592,"type":"ind","competitor":{"number":340,"identifier":"M340","skater":{"id":2776,"firstName":"Samuel","lastName":"Hart-Gorman","country":"USA","gender":"M","dateOfBirth":"2005-09-18","dateOfDeath":null,"isActive":true,"iocCode":"SSUSA11809200501","photo":null,"personalBestUrl":"https://api.isuresults.eu/skaters/2776/personal-best/","created":"2025-12-31T14:45:42.086065Z","modified":"2026-01-01T19:56:55.105189Z"}},"startNumber":7,"startLane":"I","armband":"white","rank":27,"status":0,"time":"1:16.099","timeBehind":"8.493","reskate":0,"medal":null,"isOfficial":true,"finishPhoto":null,"created":"2026-01-03T01:30:51.869699Z","modified":"2026-01-03T22:47:39.964840Z","laps":[{"number":1,"time":"18.67","passageTime":"18.679","rank":31},{"number":2,"time":"28.06","passageTime":"46.739","rank":31},{"number":3,"time":"29.36","passageTime":"1:16.099","rank":27}]},{"id":91585,"type":"ind","competitor":{"number":326,"identifier":"M326","skater":{"id":794,"firstName":"Kc","lastName":"Boutiette","country":"USA","gender":"M","dateOfBirth":"1970-04-11","dateOfDeath":null,"isActive":true,"iocCode":"SSUSA11104197001","photo":"https://media.isuresults.eu/skater/2018/10/27/794.png","personalBestUrl":"https://api.isuresults.eu/skaters/794/personal-best/","created":"2017-10-28T13:31:52.124183Z","modified":"2026-01-01T19:56:55.015853Z"}},"startNumber":3,"startLane":"O","armband":"red","rank":28,"status":0,"time":"1:16.200","timeBehind":"8.594","reskate":0,"medal":null,"isOfficial":true,"finishPhoto":null,"created":"2026-01-03T01:30:51.851601Z","modified":"2026-01-03T22:47:39.981341Z","laps":[{"number":1,"time":"18.63","passageTime":"18.636","rank":30},{"number":2,"time":"28.17","passageTime":"46.808","rank":32},{"number":3,"time":"29.39","passageTime":"1:16.200","rank":28}]},{"id":91587,"type":"ind","competitor":{"number":316,"identifier":"M316","skater":{"id":2766,"firstName":"Gavin","lastName":"Ord","country":"USA","gender":"M","dateOfBirth":"2007-04-02","dateOfDeath":null,"isActive":true,"iocCode":"SSUSA10204200701","photo":null,"personalBestUrl":"https://api.isuresults.eu/skaters/2766/personal-best/","created":"2025-12-31T14:43:45.216923Z","modified":"2026-01-01T19:56:54.954610Z"}},"startNumber":4,"startLane":"O","armband":"red","rank":29,"status":0,"time":"1:16.870","timeBehind":"9.264","reskate":0,"medal":null,"isOfficial":true,"finishPhoto":null,"created":"2026-01-03T01:30:51.857108Z","modified":"2026-01-03T22:47:39.996880Z","laps":[{"number":1,"time":"18.53","passageTime":"18.537","rank":28},{"number":2,"time":"28.10","passageTime":"46.639","rank":30},{"number":3,"time":"30.23","passageTime":"1:16.870","rank":29}]},{"id":91581,"type":"ind","competitor":{"number":322,"identifier":"M322","skater":{"id":2770,"firstName":"Jerry","lastName":"Mech","country":"USA","gender":"M","dateOfBirth":"2006-10-03","dateOfDeath":null,"isActive":true,"iocCode":"SSUSA10310200601","photo":null,"personalBestUrl":"https://api.isuresults.eu/skaters/2770/personal-best/","created":"2025-12-31T14:44:39.318653Z","modified":"2026-01-01T19:56:54.988235Z"}},"startNumber":1,"startLane":"I","armband":"white","rank":30,"status":0,"time":"1:18.753","timeBehind":"11.147","reskate":0,"medal":null,"isOfficial":true,"finishPhoto":null,"created":"2026-01-03T01:30:51.839067Z","modified":"2026-01-03T22:47:40.050972Z","laps":[{"number":1,"time":"17.82","passageTime":"17.827","rank":19},{"number":2,"time":"28.17","passageTime":"46.006","rank":24},{"number":3,"time":"32.74","passageTime":"1:18.753","rank":30}]},{"id":91583,"type":"ind","competitor":{"number":337,"identifier":"M337","skater":{"id":2775,"firstName":"Riley","lastName":"Martin","country":"USA","gender":"M","dateOfBirth":"1997-10-05","dateOfDeath":null,"isActive":true,"iocCode":"SSUSA10510199701","photo":null,"personalBestUrl":"https://api.isuresults.eu/skaters/2775/personal-best/","created":"2025-12-31T14:45:12.821103Z","modified":"2026-01-01T19:56:55.086238Z"}},"startNumber":2,"startLane":"O","armband":"red","rank":31,"status":0,"time":"1:19.269","timeBehind":"11.663","reskate":0,"medal":null,"isOfficial":true,"finishPhoto":null,"created":"2026-01-03T01:30:51.845748Z","modified":"2026-01-03T22:47:40.069194Z","laps":[{"number":1,"time":"18.13","passageTime":"18.135","rank":25},{"number":2,"time":"28.47","passageTime":"46.609","rank":29},{"number":3,"time":"32.66","passageTime":"1:19.269","rank":31}]},{"id":91591,"type":"ind","competitor":{"number":318,"identifier":"M318","skater":{"id":2768,"firstName":"Henry","lastName":"Schlichting","country":"USA","gender":"M","dateOfBirth":"2009-03-11","dateOfDeath":null,"isActive":true,"iocCode":"SSUSA11103200901","photo":null,"personalBestUrl":"https://api.isuresults.eu/skaters/2768/personal-best/","created":"2025-12-31T14:44:02.865318Z","modified":"2026-01-01T19:56:54.965903Z"}},"startNumber":6,"startLane":"O","armband":"red","rank":32,"status":0,"time":"1:31.389","timeBehind":"23.783","reskate":0,"medal":null,"isOfficial":true,"finishPhoto":null,"created":"2026-01-03T01:30:51.867301Z","modified":"2026-01-03T22:47:40.088388Z","laps":[{"number":1,"time":"27.23","passageTime":"27.234","rank":33},{"number":2,"time":"30.95","passageTime":"58.193","rank":33},{"number":3,"time":"33.19","passageTime":"1:31.389","rank":32}]},{"id":91601,"type":"ind","competitor":{"number":342,"identifier":"M342","skater":{"id":2021,"firstName":"Thomas","lastName":"Fitzgerald","country":"USA","gender":"M","dateOfBirth":"2002-04-11","dateOfDeath":null,"isActive":true,"iocCode":"SSUSA11104200201","photo":null,"personalBestUrl":"https://api.isuresults.eu/skaters/2021/personal-best/","created":"2022-01-04T19:19:06.562544Z","modified":"2026-01-01T19:56:55.116779Z"}},"startNumber":11,"startLane":"O","armband":"red","rank":null,"status":2,"time":"1:15.855","timeBehind":null,"reskate":0,"medal":null,"isOfficial":true,"finishPhoto":null,"created":"2026-01-03T01:30:51.891976Z","modified":"2026-01-03T22:47:40.106749Z","laps":[{"number":1,"time":"18.22","passageTime":"18.222","rank":26},{"number":2,"time":"27.26","passageTime":"45.489","rank":23}]}]